tradingcomdados/__init__.py
tradingcomdados/alternative_data.py
tradingcomdados/data_provider.py
tradingcomdados/funds_data.py
tradingcomdados/portfolio.py
tradingcomdados/supervised_learning.py
tradingcomdados/ta_indicators.py
tradingcomdados/unsupervised_learning.py
tradingcomdados-1.4.10.dist-info/METADATA
tradingcomdados-1.4.10.dist-info/WHEEL
tradingcomdados-1.4.10.dist-info/top_level.txt
tradingcomdados-1.4.10.dist-info/RECORD
