Metadata-Version: 2.1
Name: tradingcomdados
Version: 1.4.10
Summary: tradingcomdados
Author: Lucas Roberto Correa
Requires-Dist: pandas >=2.0.3
Requires-Dist: numpy >=1.25.2
Requires-Dist: requests >=2.31.0
Requires-Dist: requests-oauthlib >=1.3.1
Requires-Dist: requests-unixsocket >=0.2.0
Requires-Dist: joblib >=1.1.1
Requires-Dist: scikit-learn >=1.2.2
Requires-Dist: wget >=3.2
Requires-Dist: PyPDF2 >=3.0.0
